LICENSE
MANIFEST.in
README.md
package.json
setup.py
dash_spinner/DashSpinner.py
dash_spinner/__init__.py
dash_spinner/_imports_.py
dash_spinner/async-DashSpinner.js
dash_spinner/async-DashSpinner.js.map
dash_spinner/dash_spinner.min.js
dash_spinner/dash_spinner.min.js.map
dash_spinner/metadata.json
dash_spinner/package-info.json
dash_spinner.egg-info/PKG-INFO
dash_spinner.egg-info/SOURCES.txt
dash_spinner.egg-info/dependency_links.txt
dash_spinner.egg-info/top_level.txt