Metadata-Version: 2.1
Name: dash-spinner
Version: 0.0.2
Summary: Various funky loading spinners for your Dash apps
Home-page: UNKNOWN
Author: Chiranjeevi <chiranjeevi.exf@gmail.com>
License: MIT
Platform: UNKNOWN
Classifier: Framework :: Dash
Classifier: Programming Language :: Python :: 3.6
Classifier: Programming Language :: Python :: 3.7
Classifier: Programming Language :: Python :: 3.8
Classifier: Programming Language :: Python :: 3.9
Classifier: Programming Language :: Python :: 3.10
